MANIFEST.in
README.rst
requirements.txt
setup.py
agency/__init__.py
agency/apps.py
agency/urls.py
agency/views.py
agency/migrations/__init__.py
candidate/__init__.py
candidate/forms.py
candidate/tests.py
candidate/urls.py
candidate/views.py
dashboard/__init__.py
dashboard/forms.py
dashboard/tasks.py
dashboard/tests.py
dashboard/urls.py
dashboard/views.py
jobsp/__init__.py
jobsp/celery.py
jobsp/middlewares.py
jobsp/settings.py
jobsp/settings_local.py
jobsp/settings_server.py
jobsp/thumbnailname.py
jobsp/urls.py
jobsp/wsgi.py
mpcomp/__init__.py
mpcomp/atom_client.py
mpcomp/atom_data.py
mpcomp/aws.py
mpcomp/client.py
mpcomp/contacts.py
mpcomp/core.py
mpcomp/data.py
mpcomp/facebook.py
mpcomp/gauth.py
mpcomp/gdata_data.py
mpcomp/http_core.py
mpcomp/views.py
opensource_job_portal.egg-info/PKG-INFO
opensource_job_portal.egg-info/SOURCES.txt
opensource_job_portal.egg-info/dependency_links.txt
opensource_job_portal.egg-info/top_level.txt
peeldb/__init__.py
peeldb/admin.py
peeldb/backends.py
peeldb/context_processors.py
peeldb/models.py
peeldb/search_indexes.py
peeldb/management/__init__.py
peeldb/management/commands/__init__.py
peeldb/management/commands/load_initial_data.py
peeldb/migrations/0001_initial.py
peeldb/migrations/0002_blogattachment.py
peeldb/migrations/0003_user_agency_admin.py
peeldb/migrations/0004_auto_20170211_1724.py
peeldb/migrations/0005_auto_20170211_1738.py
peeldb/migrations/0006_auto_20170211_1817.py
peeldb/migrations/0007_auto_20170213_1547.py
peeldb/migrations/0008_company_campaign_icon.py
peeldb/migrations/0009_agencyworklog.py
peeldb/migrations/0010_agencyworklog_timegap.py
peeldb/migrations/0011_auto_20170214_1842.py
peeldb/migrations/0012_auto_20170223_1712.py
peeldb/migrations/0013_auto_20170321_1431.py
peeldb/migrations/0014_auto_20170323_1106.py
peeldb/migrations/0015_auto_20170422_1154.py
peeldb/migrations/0016_jobpost_published_on.py
peeldb/migrations/0017_auto_20170704_1921.py
peeldb/migrations/0018_user_alternate_mobile.py
peeldb/migrations/0019_company_created_from.py
peeldb/migrations/0020_auto_20170717_1230.py
peeldb/migrations/0021_user_resume_text.py
peeldb/migrations/0022_user_referer.py
